{
  "indexes": [
    {
      "collectionGroup": "expenses",
      "queryScope": "COLLECTION",
      "fields": [
        {
          "fieldPath": "userExpenses",
          "order": "ASCENDING"
        },
        {
          "fieldPath": "purchase_date",
          "order": "ASCENDING"
        }
      ]
    },
    {
      "collectionGroup": "expenses",
      "queryScope": "COLLECTION",
      "fields": [
        {
          "fieldPath": "userExpenses",
          "order": "ASCENDING"
        },
        {
          "fieldPath": "payment_type",
          "order": "ASCENDING"
        },
        {
          "fieldPath": "purchase_date",
          "order": "DESCENDING"
        }
      ]
    }
  ]
}